coveo_settings/__init__.py
coveo_settings/annotations.py
coveo_settings/any_setting.py
coveo_settings/bool_setting.py
coveo_settings/dict_setting.py
coveo_settings/exceptions.py
coveo_settings/float_setting.py
coveo_settings/int_setting.py
coveo_settings/mock.py
coveo_settings/path_setting.py
coveo_settings/py.typed
coveo_settings/setting_abc.py
coveo_settings/settings.py
coveo_settings/string_setting.py
coveo_settings/validation.py
coveo_settings-3.0.dist-info/METADATA
coveo_settings-3.0.dist-info/WHEEL
coveo_settings-3.0.dist-info/RECORD
